daehan_mlutil/__init__.py
daehan_mlutil/utilities.py
daehan_mlutil-0.1.4.dist-info/LICENSE
daehan_mlutil-0.1.4.dist-info/METADATA
daehan_mlutil-0.1.4.dist-info/WHEEL
daehan_mlutil-0.1.4.dist-info/top_level.txt
daehan_mlutil-0.1.4.dist-info/RECORD
