Metadata-Version: 2.1
Name: daehan-mlutil
Version: 0.1.4
Summary: A ML utilities package
Home-page: https://github.com/daehan-lim/mlutil
Author: Daehan Lim
Author-email: daehanlim@g.cnu.ac.kr
License: MIT License
Classifier: Development Status :: 1 - Planning
Classifier: Intended Audience :: Science/Research
Classifier: License :: OSI Approved :: MIT License
Classifier: Operating System :: POSIX :: Linux
Classifier: Programming Language :: Python :: 3
Classifier: Programming Language :: Python :: 3.6
Classifier: Programming Language :: Python :: 3.7
Classifier: Programming Language :: Python :: 3.8
Classifier: Programming Language :: Python :: 3.9
Classifier: Programming Language :: Python :: 3.10
License-File: LICENSE
